{"development_add-event-action.md":"c19e6cde","development_add-library-component.md":"0683a9ef","development_build.md":"f8105ff1","development_coding-style.md":"e835afea","development_dictionary-style.md":"95d708a2","development_dictionary.md":"44d68104","development_git-style.md":"cbe2107b","development_icon.md":"5123f83e","development_lint.md":"c538414c","development_prepare.md":"b9d018ab","development_question.md":"46e02214","development_start.md":"fe91e8b7","development_style-design.md":"189b7c5b","development_typescript.md":"c3ccf2d4","development_unit-test.md":"1065a8ea","development_update-by-git.md":"48edcfe1","guide_component.md":"5e7bdae2","guide_event-and-action.md":"82b1aad2","guide_question.md":"6b0f4521","guide_style.md":"f15aea53","guide_summary.md":"c0f057a0","index.md":"a013ee70","team.md":"207ac638"}
